setup.cfg
setup.py
custom_orm/__init__.py
custom_orm/constants.py
custom_orm/db.py
custom_orm/exceptions.py
custom_orm/loader.py
custom_orm/test.py
custom_orm.egg-info/PKG-INFO
custom_orm.egg-info/SOURCES.txt
custom_orm.egg-info/dependency_links.txt
custom_orm.egg-info/not-zip-safe
custom_orm.egg-info/top_level.txt