Metadata-Version: 2.1
Name: custom-orm
Version: 0.5
Summary: custom ORM
Home-page: UNKNOWN
Author-email: aleks.zhuravlev2002@mail.ru
License: UNKNOWN
Platform: UNKNOWN
